{
  "main": {
    "id": "c4b548e20567d06c",
    "type": "split",
    "children": [
      {
        "id": "a8d9449162ce089c",
        "type": "tabs",
        "children": [
          {
            "id": "eae4d2cae21ffbf0",
            "type": "leaf",
            "state": {
              "type": "markdown",
              "state": {
                "file": "计算机组成原理/待分类/CPU缓存一致性.md",
                "mode": "source",
                "source": false
              },
              "icon": "lucide-file",
              "title": "CPU缓存一致性"
            }
          },
          {
            "id": "08383a2f56ae4812",
            "type": "leaf",
            "state": {
              "type": "markdown",
              "state": {
                "file": "CPP/C2CPP/C2CPP.md",
                "mode": "source",
                "source": false
              },
              "icon": "lucide-file",
              "title": "C2CPP"
            }
          }
        ]
      }
    ],
    "direction": "vertical"
  },
  "left": {
    "id": "cd3278d30764ab2f",
    "type": "split",
    "children": [
      {
        "id": "ce57341dd2d7d0cb",
        "type": "tabs",
        "children": [
          {
            "id": "7ddc64b2e3c9b5c8",
            "type": "leaf",
            "state": {
              "type": "file-explorer",
              "state": {
                "sortOrder": "custom",
                "autoReveal": false
              },
              "icon": "lucide-folder-closed",
              "title": "文件列表"
            }
          },
          {
            "id": "d7694db761056d1c",
            "type": "leaf",
            "state": {
              "type": "search",
              "state": {
                "query": "",
                "matchingCase": false,
                "explainSearch": false,
                "collapseAll": true,
                "extraContext": false,
                "sortOrder": "alphabetical"
              },
              "icon": "lucide-search",
              "title": "搜索"
            }
          },
          {
            "id": "6d04244bcd16cc79",
            "type": "leaf",
            "state": {
              "type": "starred",
              "state": {},
              "icon": "lucide-file",
              "title": "插件不再活动"
            }
          },
          {
            "id": "fa7bed5878afb8af",
            "type": "leaf",
            "state": {
              "type": "bookmarks",
              "state": {},
              "icon": "lucide-bookmark",
              "title": "Bookmarks"
            }
          }
        ]
      }
    ],
    "direction": "horizontal",
    "width": 279.5
  },
  "right": {
    "id": "989a0ed08fe1a7b2",
    "type": "split",
    "children": [
      {
        "id": "fee78256467ec87d",
        "type": "tabs",
        "children": [
          {
            "id": "062701aa100a3f19",
            "type": "leaf",
            "state": {
              "type": "backlink",
              "state": {
                "file": "嵌入式基础/软件层技术/应用层通信协议/Modbus.md",
                "collapseAll": true,
                "extraContext": false,
                "sortOrder": "alphabetical",
                "showSearch": false,
                "searchQuery": "",
                "backlinkCollapsed": false,
                "unlinkedCollapsed": true
              },
              "icon": "links-coming-in",
              "title": "Modbus 的反向链接列表"
            }
          },
          {
            "id": "21dd06d587b3ddc7",
            "type": "leaf",
            "state": {
              "type": "outgoing-link",
              "state": {
                "file": "操作系统/Linux原理专题/系统调用专题/IO多路复用接口(select、poll、epoll).md",
                "linksCollapsed": false,
                "unlinkedCollapsed": true
              },
              "icon": "links-going-out",
              "title": "IO多路复用接口(select、poll、epoll) 的出链列表"
            }
          },
          {
            "id": "3c997c4dde5bf122",
            "type": "leaf",
            "state": {
              "type": "tag",
              "state": {
                "sortOrder": "frequency",
                "useHierarchy": true
              },
              "icon": "lucide-tags",
              "title": "标签"
            }
          },
          {
            "id": "1bc30e82fd7b9190",
            "type": "leaf",
            "state": {
              "type": "outline",
              "state": {
                "file": "计算机组成原理/待分类/CPU缓存一致性.md",
                "followCursor": false,
                "showSearch": false,
                "searchQuery": ""
              },
              "icon": "lucide-list",
              "title": "CPU缓存一致性 的大纲"
            }
          },
          {
            "id": "d976f59277efb42c",
            "type": "leaf",
            "state": {
              "type": "git-view",
              "state": {},
              "icon": "git-pull-request",
              "title": "Source Control"
            }
          },
          {
            "id": "85a99ffcd4adfabe",
            "type": "leaf",
            "state": {
              "type": "mermaid-toolbar-view",
              "state": {},
              "icon": "trident-custom",
              "title": "Mermaid Toolbar"
            }
          }
        ],
        "currentTab": 3
      }
    ],
    "direction": "horizontal",
    "width": 317.5
  },
  "left-ribbon": {
    "hiddenItems": {
      "switcher:打开快速切换": false,
      "graph:查看关系图谱": false,
      "canvas:新建白板": false,
      "command-palette:打开命令面板": false,
      "audio-recorder:开始/结束录音": false,
      "obsidian-git:Open Git source control": false,
      "webpage-html-export:Export as HTML": false,
      "mermaid-tools:Open Mermaid Toolbar": false,
      "obsidian42-brat:BRAT": false
    }
  },
  "active": "eae4d2cae21ffbf0",
  "lastOpenFiles": [
    "计算机组成原理/Resources/Pasted image 20250221133107.png",
    "计算机组成原理/待分类/CPU缓存一致性.md",
    "Linux内核原理及其开发/应试笔记与八股.md",
    "计算机组成原理/待分类",
    "CPP/C2CPP/C2CPP.md",
    "Linux内核原理及其开发/Linux驱动开发笔记.md",
    "计算机组成原理/计算机组成原理应试学习.md",
    "计算机组成原理/常用存储器.md",
    "嵌入式基础/接口技术/Readme.md",
    "嵌入式基础/接口技术/SPI/SPI总线标准.md",
    "嵌入式基础/接口技术/I2C/I2C总线标准.md",
    "嵌入式基础/接口技术/CAN/CAN总线协议标准.md",
    "嵌入式基础/接口技术/串口/串口总线标准.md",
    "计算机组成原理/第一章 计算机系统概述/第一章 计算机系统概述.md",
    "操作系统/用户态开发/IPC/Linux用户态IPC.md",
    "STM32开发/STM32开发笔记.md",
    "机器学习/应试笔记与八股.md",
    "计算机网络/计算机网络非应试拓展/TCP标准.md",
    "计算机网络/基础应试学习/计算机网络应试学习.md",
    "计算机网络/基础应试学习/第四章 网络层/第四章 网络层.md",
    "计算机网络/基础应试学习/第一章 计算机网络体系结构/第一章 计算机网络体系结构.md",
    "计算机网络/基础应试学习/第六章 应用层/第六章 应用层.md",
    "软件工程/软件工程应试笔记.md",
    "电子技术/基本元器件/MOSFET.md",
    "生活常识/国家标准/生活常识的国家标准.md",
    "生活常识/数码/电脑IO接口与协议.md",
    "生活常识/医学健康/常见病症.md",
    "CPP/Resources/C数据类型.canvas",
    "Linux内核原理及其开发/内核原理专题/内存管理专题",
    "生活常识/二手购物",
    "生活常识/Resources/3a4f2e672eb17167e81a9907cf8642f.png",
    "Resources/3a4f2e672eb17167e81a9907cf8642f 1.png",
    "操作系统/基础应试学习/第二章 进程与线程",
    "操作系统/基础应试学习/第一章 计算机系统概述",
    "操作系统/基础应试学/未命名",
    "操作系统/基础应试学习",
    "Linux内核原理及其开发/内核原理专题/系统调用专题/文件子系统",
    "Resources/Pasted image 20240203021517.png",
    "Linux内核原理及其开发/Resources/Pasted image 20241124170145.png",
    "Linux内核原理及其开发/Resources/Pasted image 20241124170623.png",
    "Linux内核原理及其开发/Resources/~$$type.h.~vsdx",
    "Linux内核原理及其开发/Resources/type.h.vsdx",
    "操作系统/Resources/MobaXterm_C1PkrYnmXJ.png",
    "操作系统/Resources/0261.png",
    "操作系统/Resources/git_ignored/UNIX环境高级编程（中文第三版） (W. Richard Stevens etc.) (Z-Library)/0261.png",
    "Resources/8619b62ac43800a3e18be2330e906e05.png",
    "嵌入式基础/接口技术/未命名.canvas"
  ]
}